nikki30201/__init__.py
nikki30201/lib2.py
nikki30201-0.2.dist-info/METADATA
nikki30201-0.2.dist-info/WHEEL
nikki30201-0.2.dist-info/top_level.txt
nikki30201-0.2.dist-info/RECORD
