Metadata-Version: 2.1
Name: nikki30201
Version: 0.2
Summary: Taiwan No. 1
Home-page: http://github.com/storborg/nikki30201
Author: Michael Chen
Author-email: flyingcircus@example.com
License: MIT
Platform: UNKNOWN
